amps/__init__.py
amps_py-0.1.8.dist-info/LICENSE
amps_py-0.1.8.dist-info/METADATA
amps_py-0.1.8.dist-info/WHEEL
amps_py-0.1.8.dist-info/top_level.txt
amps_py-0.1.8.dist-info/RECORD
