Metadata-Version: 2.1
Name: amps-py
Version: 0.1.8
Summary: Package for Interfacing with AMPS from Agile Data Inc.
Home-page: https://mftlabs.github.io/amps-py
Author: Abhay Ram
Author-email: abhayram@hub4edi.com
Project-URL: Bug Tracker, https://github.com/mftlabs/amps-py/issues
Classifier: Programming Language :: Python :: 3
Classifier: License :: OSI Approved :: MIT License
Classifier: Operating System :: OS Independent
Requires-Python: >=3.6
License-File: LICENSE
